cuthbert/__init__.py
cuthbert/filtering.py
cuthbert/inference.py
cuthbert/smoothing.py
cuthbert/utils.py
cuthbert-0.0.2.dist-info/licenses/LICENSE
cuthbertlib/__init__.py
cuthbertlib/types.py
cuthbert-0.0.2.dist-info/METADATA
cuthbert-0.0.2.dist-info/WHEEL
cuthbert-0.0.2.dist-info/top_level.txt
cuthbert-0.0.2.dist-info/RECORD
