Metadata-Version: 2.4
Name: cuthbert
Version: 0.0.2
Summary: State-space model inference with JAX
Author-email: Sam Duffield <s@mduffield.com>, Sahel Iqbal <sahel13miqbal@proton.me>, Adrien Corenflos <adrien.corenflos.stats@gmail.com>
License: Apache-2.0
Requires-Python: >=3.10
License-File: LICENSE
Requires-Dist: jax>=0.4.35
Requires-Dist: numba>=0.60.0
Provides-Extra: tests
Requires-Dist: chex; extra == "tests"
Requires-Dist: pre-commit; extra == "tests"
Requires-Dist: ruff; extra == "tests"
Requires-Dist: pyright; extra == "tests"
Requires-Dist: pytest; extra == "tests"
Requires-Dist: pytest-xdist; extra == "tests"
Requires-Dist: entangled-cli; python_version >= "3.12" and extra == "tests"
Provides-Extra: docs
Requires-Dist: mkdocs-material; extra == "docs"
Requires-Dist: mkdocs-include-markdown-plugin; extra == "docs"
Requires-Dist: mkdocstrings-python; extra == "docs"
Provides-Extra: examples
Requires-Dist: matplotlib; extra == "examples"
Requires-Dist: pandas; extra == "examples"
Requires-Dist: pandas-stubs; extra == "examples"
Requires-Dist: yfinance; extra == "examples"
Requires-Dist: dynamax; extra == "examples"
Requires-Dist: ipython; extra == "examples"
Requires-Dist: tfp-nightly[jax]; extra == "examples"
Dynamic: license-file
